fetchy/__init__.py
fetchy/blueprint.py
fetchy/cli/__init__.py
fetchy/cli/application.py
fetchy/cli/commands/blueprint.py
fetchy/cli/commands/command.py
fetchy/cli/commands/dockerize.py
fetchy/context.py
fetchy/dfs.py
fetchy/dockerfile.py
fetchy/fetchy.py
fetchy/plugins/__init__.py
fetchy/plugins/packages/__init__.py
fetchy/plugins/packages/debian.py
fetchy/plugins/packages/dependency.py
fetchy/plugins/packages/downloader.py
fetchy/plugins/packages/mirror.py
fetchy/plugins/packages/package.py
fetchy/plugins/packages/packages.py
fetchy/plugins/packages/parser.py
fetchy/plugins/packages/repository.py
fetchy/plugins/packages/source.py
fetchy/plugins/packages/version.py
fetchy/plugins/plugin.py
fetchy/utils.py
fetchy-0.1.8.dist-info/entry_points.txt
fetchy-0.1.8.dist-info/LICENSE
fetchy-0.1.8.dist-info/WHEEL
fetchy-0.1.8.dist-info/METADATA
fetchy-0.1.8.dist-info/RECORD
